[{"nim":"15109003","name":"Yudo Hermawan"},{"nim":"15109006","name":"Harya Adhim"},{"nim":"15109037","name":"Aidil Akbar"},{"nim":"15109040","name":"Ivo Sofyan Ulfy Pranata N"},{"nim":"15109049","name":"Fariz Ubaidillah Rasyid"},{"nim":"15109057","name":"Chakras Andika Kuntjoro"},{"nim":"15109062","name":"Gusmilan Pratiantono"},{"nim":"15109064","name":"Doni Andrianto"},{"nim":"15109100","name":"Hadi M Subandi"},{"nim":"15110002","name":"Muhammad Syirazi"},{"nim":"15110003","name":"Rian Pratama Putra"},{"nim":"15110005","name":"Aan Agragunansyah Toyiti"},{"nim":"15110008","name":"Bregas D Suryowibowo"},{"nim":"15110024","name":"Gifial Fauzi S"},{"nim":"15110025","name":"Muhammad Luthfan Naufal"},{"nim":"15110055","name":"Anisa Karina"},{"nim":"15110058","name":"Muhammad Fariz Yudha"},{"nim":"15110065","name":"Herjuno Jati Darpito"},{"nim":"15110082","name":"Ahmad Fadel Ahdiakusuma"},{"nim":"15110084","name":"Muhammad Rausyan Fikri"},{"nim":"15110094","name":"Ramadhan Hidayatur Rahman"},{"nim":"15110099","name":"Aditya Hadiyan"},{"nim":"15110105","name":"Camaraderie Al Abraar"},{"nim":"15111001","name":"Jefri Hendri Adriano"},{"nim":"15111002","name":"Aditya Fikri Ghozali"},{"nim":"15111003","name":"Clava Pratama P Ginting"},{"nim":"15111004","name":"Muh Aqsyah"},{"nim":"15111005","name":"Nur Ainiyah"},{"nim":"15111006","name":"Alwidya Angga Safitri"},{"nim":"15111007","name":"Lukman Kadafi"},{"nim":"15111008","name":"Muhammad Taufik"},{"nim":"15111009","name":"Daniella"},{"nim":"15111010","name":"Satrio Muhammad Alif"},{"nim":"15111011","name":"Ferdinand Mangaratua Simatupan"},{"nim":"15111012","name":"Bimar Anugrah"},{"nim":"15111013","name":"Syamora Setyadi Supardan"},{"nim":"15111014","name":"Wilma Fitri"},{"nim":"15111015","name":"Rianto"},{"nim":"15111016","name":"Mona Ardika"},{"nim":"15111017","name":"Ayu Permatasari"},{"nim":"15111018","name":"Nia Pradinawati"},{"nim":"15111019","name":"Nanda Sachra Y"},{"nim":"15111020","name":"Rifqi Muhammad Harrys"},{"nim":"15111021","name":"Chandra Adi Yaksa"},{"nim":"15111022","name":"Arie Januar Fazriansyah"},{"nim":"15111023","name":"Ade Putra"},{"nim":"15111024","name":"Vannia Alfiani Dalimunthe"},{"nim":"15111025","name":"Siti Hajar Aswad"},{"nim":"15111026","name":"Muhammad Nizar Abdul Basith"},{"nim":"15111027","name":"Pirma Hutajulu"},{"nim":"15111028","name":"Adi Poetra Pratama"},{"nim":"15111029","name":"Wanda Juwita"},{"nim":"15111030","name":"Gandhi Malau"},{"nim":"15111031","name":"Nadya Amanda Utari"},{"nim":"15111032","name":"Dara Fara Dilla Ulfiani"},{"nim":"15111033","name":"Diana Barirotuttaqiyyah"},{"nim":"15111034","name":"Bhima Bhagaskara"},{"nim":"15111035","name":"Anindyasty Rofiqoh"},{"nim":"15111036","name":"Riandi Namara"},{"nim":"15111037","name":"Angga Fauzi Rohman"},{"nim":"15111038","name":"Tika Mutiara Ula"},{"nim":"15111039","name":"Cygnus Di Aprilio"},{"nim":"15111040","name":"Isnainnur Iman"},{"nim":"15111041","name":"Chaikal Amrullah"},{"nim":"15111042","name":"Farah Diba"},{"nim":"15111043","name":"Arinka Aninditya"},{"nim":"15111044","name":"Yugi Pratama"},{"nim":"15111045","name":"Joan Novianti Johnny"},{"nim":"15111046","name":"Eka Fidiyanti"},{"nim":"15111047","name":"Alif Fattah Adzani"},{"nim":"15111048","name":"Dinan Abdul Khalik"},{"nim":"15111049","name":"Aria Windu Pratama"},{"nim":"15111051","name":"Ekmi Gasari Sanjaya"},{"nim":"15111052","name":"Rio Raharja"},{"nim":"15111053","name":"Qumil Laila"},{"nim":"15111054","name":"Rizki Baihaqi"},{"nim":"15111055","name":"Rm Enrico Dwidhanto Indrawan"},{"nim":"15111056","name":"Rurin Puspita Dewi"},{"nim":"15111057","name":"Geta Ayu Ferdiyanti"},{"nim":"15111058","name":"Yasmine Citra Dian Utami"},{"nim":"15111059","name":"Achmad Faris"},{"nim":"15111060","name":"Usriyah"},{"nim":"15111061","name":"Armand Maulana Yusuf"},{"nim":"15111062","name":"Nadia Shalehah"},{"nim":"15111063","name":"Dion Qairawan"},{"nim":"15111064","name":"Andrean Eka Lucianto"},{"nim":"15111065","name":"Afri Yudhawan"},{"nim":"15111066","name":"Intan Ika Apriani"},{"nim":"15111067","name":"Tougoss S B"},{"nim":"15111068","name":"Tia Hartiani Kusaeri"},{"nim":"15111069","name":"Inung Wahaning Nurani"},{"nim":"15111070","name":"Dwiky Himawan Prabowo"},{"nim":"15111071","name":"Siti Herdiati Muharromah"},{"nim":"15111072","name":"Muhammad Irvandi H"},{"nim":"15111073","name":"Ananto Indria Pamungkas"},{"nim":"15111074","name":"Fuad Ramadhana"},{"nim":"15111075","name":"Arif Surahman"},{"nim":"15111076","name":"Ghaniy Nugrahantoro"},{"nim":"15111077","name":"Gilang Pradana"},{"nim":"15111078","name":"Nurul Sandy Putri"},{"nim":"15111079","name":"Furqan"},{"nim":"15111080","name":"Mochamad Arif Supiadin"},{"nim":"15111081","name":"Thalya Putri Herdhiyanti"},{"nim":"15111082","name":"Muchammad Ibrahim Ulinnuha"},{"nim":"15111083","name":"Sari Widya Apriyani"},{"nim":"15111084","name":"Evarina Engelina"},{"nim":"15111085","name":"Ribka Cahyaning Siwi"},{"nim":"15111086","name":"Aning Haryati"},{"nim":"15111087","name":"Nunghatta Samodra W"},{"nim":"15111088","name":"Andi Putra Parlindungan"},{"nim":"15111089","name":"Triananda Ufuk Agung Nugroho"},{"nim":"15111090","name":"Adnan Ananda"},{"nim":"15111091","name":"Ratu Gina Adawiyah Iskandar"},{"nim":"15111092","name":"Hudan Asharyanto"},{"nim":"15111093","name":"Randu Kalifa Syabana"},{"nim":"15111094","name":"Dyah Ayu Ritma Ratri"},{"nim":"15111095","name":"Arinda Syakura Afiata"},{"nim":"15111096","name":"Fadel Muhammad"},{"nim":"15111097","name":"Aulia Luqman Lionar"},{"nim":"15111098","name":"Muhammad Rafi Respati"},{"nim":"15111099","name":"Joy Arsyad Natabraja"},{"nim":"15111100","name":"Teo Hogy Wijaya"},{"nim":"15111101","name":"Kramer Oktobrinus Napitupulu"},{"nim":"15111102","name":"Dolly Saputra"},{"nim":"15111103","name":"Wintia Arindina"},{"nim":"15111104","name":"Bima Ulma"},{"nim":"15111105","name":"Kevin Nathanael Sibarani"},{"nim":"15111106","name":"Achmad Amri Dharma Wangsa"},{"nim":"15111107","name":"Ri'yu Diawan Fuadhadi"},{"nim":"15111108","name":"Kandhila Nuriza Primaswari"},{"nim":"15112001","name":"Mifa Yaumil Ihsani"},{"nim":"15112002","name":"Kania Permata Sari"},{"nim":"15112003","name":"Sahat Jeriko Pardede"},{"nim":"15112004","name":"Abiyyu Hilmy Rusin"},{"nim":"15112005","name":"Silmi Fawzya Ludya"},{"nim":"15112006","name":"Gerry Anthony"},{"nim":"15112007","name":"Dyah Ayu Retnowati"},{"nim":"15112008","name":"Septyanto"},{"nim":"15112009","name":"Yudha Bella Adikara Putra"},{"nim":"15112010","name":"Ririn Indahyani"},{"nim":"15112011","name":"Daffa Gifary M P"},{"nim":"15112012","name":"R Derian Rachmanda S"},{"nim":"15112013","name":"Rezky Heidi Saputro"},{"nim":"15112014","name":"Jonathan Harpin S M"},{"nim":"15112015","name":"Chuslul Badar"},{"nim":"15112016","name":"Daniel Arianto Tampubolon"},{"nim":"15112017","name":"Putri Rahmadani"},{"nim":"15112018","name":"Aris Stiawan"},{"nim":"15112019","name":"Muhamad Iqbal Triputra S"},{"nim":"15112020","name":"Widwiyaswati Roosita Dewi"},{"nim":"15112021","name":"M Fahru Reza Hakim"},{"nim":"15112022","name":"Dian Tomy Wardana"},{"nim":"15112023","name":"Paulus Junior Saragih"},{"nim":"15112024","name":"Nitya Silfarera"},{"nim":"15112025","name":"Arief Rahman"},{"nim":"15112026","name":"Shafira Irmarini"},{"nim":"15112027","name":"Dini Aprilia Norvyani"},{"nim":"15112028","name":"Ressy Fitria"},{"nim":"15112029","name":"Michael T Tasliman"},{"nim":"15112030","name":"Ifa Hanifah"},{"nim":"15112031","name":"Alexander Daniel Pratama"},{"nim":"15112032","name":"Dinna Amelia"},{"nim":"15112033","name":"Jingga Sekar Langit"},{"nim":"15112034","name":"Yudhistira Aditya Ww"},{"nim":"15112035","name":"Dzulkhi Yudha Pratama"},{"nim":"15112036","name":"Fadel Muhammad"},{"nim":"15112037","name":"Fadhilur Rahman"},{"nim":"15112038","name":"Nindytha Mugyaning Tyas"},{"nim":"15112039","name":"Firza Adrian G Munthe"},{"nim":"15112040","name":"Torang Arthur Nabiel"},{"nim":"15112041","name":"Dominicus Teti"},{"nim":"15112042","name":"Dora Anna Hutajulu"},{"nim":"15112043","name":"Wachid Nuraziz Musthafa"},{"nim":"15112044","name":"Pramudya Septian Permadi"},{"nim":"15112045","name":"Giovanni Cynthia P"},{"nim":"15112046","name":"Zaky Abdurrasyid M"},{"nim":"15112047","name":"Muhammad Ihsan"},{"nim":"15112048","name":"Aulia Aninditya Rangsang"},{"nim":"15112049","name":"Stevan Lumbantoruan"},{"nim":"15112050","name":"Patih Fathin Rizal"},{"nim":"15112051","name":"Pidi Miandra"},{"nim":"15112052","name":"Faisal Widodo Bancin"},{"nim":"15112054","name":"Tahjudil Witra"},{"nim":"15112055","name":"Dirga Prana Tarigan"},{"nim":"15112056","name":"Refi Rizqi Ramadian"},{"nim":"15112057","name":"Yolanda Gina Novita"},{"nim":"15112058","name":"Isfan Anugrah Ramadhan"},{"nim":"15112059","name":"Akbar Wahyu Nugraha"},{"nim":"15112060","name":"Annisaa Dyah Adani"},{"nim":"15112061","name":"Puspita Indriani"},{"nim":"15112062","name":"Ade Prachodayat"},{"nim":"15112063","name":"Sherley Agustine"},{"nim":"15112064","name":"Kevin Adiyasa"},{"nim":"15112065","name":"Bagoes Dwi Ramdhani"},{"nim":"15112066","name":"Jery Adrian"},{"nim":"15112067","name":"Ikhwan Aly Rhosidi"},{"nim":"15112068","name":"Arinta Rosana"},{"nim":"15112069","name":"Setia Wulandari"},{"nim":"15112070","name":"Yola Asis Herawati"},{"nim":"15112071","name":"Dirga Imam Gozali"},{"nim":"15112072","name":"Dian Kristiawan"},{"nim":"15112073","name":"Isti Sandita"},{"nim":"15112074","name":"Andika Hadi Hutama"},{"nim":"15112075","name":"Muhammad Mu'aqil Uham"},{"nim":"15112076","name":"Mohamad Hafiz Al Faza"},{"nim":"15112077","name":"Qoriatun Nafishoh"},{"nim":"15112078","name":"Tombayu Amadeo Hidayat"},{"nim":"15112079","name":"Alvin Ridho Fadhilah"},{"nim":"15112080","name":"Mei Handayani"},{"nim":"15112081","name":"Abdi Pistari M"},{"nim":"15112082","name":"Suchi Rahmadani"},{"nim":"15112083","name":"Ajeng Salmayarista"},{"nim":"15112084","name":"Totok Agus Widodo"},{"nim":"15112085","name":"Mohamad Nur Fajri"},{"nim":"15112086","name":"Fuad Fithratur Rahman"},{"nim":"15112087","name":"Odie Syahrozi"},{"nim":"15112088","name":"Rizal Trytama Sukirno Putra"},{"nim":"15112089","name":"Bintang Rahmat Wananda"},{"nim":"15112090","name":"Atifah Rabbani"},{"nim":"15112091","name":"Oriza Subekti"},{"nim":"15112092","name":"Febriana Kuscahyadi"},{"nim":"15112093","name":"Eka Fitriani"},{"nim":"15112094","name":"Michelle Natasa"},{"nim":"15112095","name":"Alify Raissa Octaviani"},{"nim":"15112096","name":"Satrio Wicaksono"},{"nim":"15112097","name":"Hanandya Ajeng Niti Pratiwi"},{"nim":"15112098","name":"Sabilillah Nurkalista"},{"nim":"15112099","name":"Ivan Flobert Gultom"},{"nim":"15112100","name":"Anshar Ajatasatru"},{"nim":"15112101","name":"Teguh Oktaprima"},{"nim":"15112102","name":"Annissaa Fauziah"},{"nim":"15112103","name":"Marulitua Ignatius"},{"nim":"15112104","name":"Fabhianto Maoludyo"},{"nim":"15112105","name":"Andika Virdian"},{"nim":"15113001","name":"Ola Khusnul Khotimah"},{"nim":"15113002","name":"Berlusconi Tri Panraya Purba"},{"nim":"15113003","name":"Aulia Fajrina"},{"nim":"15113004","name":"Puti Nabila Riyadi"},{"nim":"15113005","name":"Randi Nayaka Paramandana"},{"nim":"15113006","name":"Andi Firdaus"},{"nim":"15113007","name":"Baginda Echasio"},{"nim":"15113008","name":"Tantan Tasni Ramdani"},{"nim":"15113009","name":"Asthina Novita Syanur"},{"nim":"15113011","name":"Alfath Notariil"},{"nim":"15113012","name":"Nathania Stephanie R K"},{"nim":"15113013","name":"Azaria Anggana Laras"},{"nim":"15113014","name":"Dony Bagaskara"},{"nim":"15113015","name":"Septian Pardomuan Siburian"},{"nim":"15113016","name":"Debby Nurliza Ulhaq"},{"nim":"15113017","name":"Grieska Adhi Parwannitya"},{"nim":"15113018","name":"Athif Muhaimin"},{"nim":"15113019","name":"Handika Tarigan"},{"nim":"15113020","name":"David Nikolas Tumanggor"},{"nim":"15113021","name":"Yesi Yustiawati"},{"nim":"15113022","name":"Nita Dwi Astuti"},{"nim":"15113023","name":"Muhammad Rafsanjani"},{"nim":"15113024","name":"Farah Nafisa Ariadji"},{"nim":"15113025","name":"Iqbal Fachrurrazie Surahman"},{"nim":"15113026","name":"Sangkap Tua"},{"nim":"15113027","name":"Ivon Nurjannah"},{"nim":"15113028","name":"Sahat Natanael Tampubolon"},{"nim":"15113029","name":"Wulan Puspita Angraini"},{"nim":"15113030","name":"Vella Ahalla Hulaifah Somantri"},{"nim":"15113031","name":"Abilla Pramita Dewi"},{"nim":"15113032","name":"Septandry Am Manik"},{"nim":"15113033","name":"Norman Arif Muhammad"},{"nim":"15113034","name":"Desti Ayunda"},{"nim":"15113035","name":"Muhammad Pandito Pratama"},{"nim":"15113036","name":"Rainaldy Dwiatmoko"},{"nim":"15113037","name":"R Fiddin Yurizka Firdaus"},{"nim":"15113038","name":"Azhar Fuadi Siregar"},{"nim":"15113039","name":"Willy Yanto"},{"nim":"15113040","name":"Huda Al Hakim"},{"nim":"15113041","name":"Razky Rahadian Sugiarto"},{"nim":"15113042","name":"Fadel Ilhami Nasr"},{"nim":"15113043","name":"Setya Dhana Santika Aji"},{"nim":"15113044","name":"Hazizah Aulia Rachmah"},{"nim":"15113045","name":"Saddam Chair"},{"nim":"15113046","name":"Akbar Perdana Putra"},{"nim":"15113047","name":"Fathia Zulfati Shabrina"},{"nim":"15113048","name":"Mila Rachmalia"},{"nim":"15113049","name":"Dadang Iswanto Putro"},{"nim":"15113050","name":"Rizky Afdal"},{"nim":"15113051","name":"Arry Pramansyah"},{"nim":"15113052","name":"Jan Ivan F H Manurung"},{"nim":"15113053","name":"Tio Akira Al Rasyid Darwin"},{"nim":"15113054","name":"Hani"},{"nim":"15113055","name":"R Resa Adam Gunawan"},{"nim":"15113056","name":"Lufta Erwin Winata"},{"nim":"15113057","name":"Bintang Andaru"},{"nim":"15113058","name":"Muhammad Najmi Naufal"},{"nim":"15113059","name":"Intan Trilestari"},{"nim":"15113060","name":"Suhartawati Sholihah"},{"nim":"15113061","name":"Anindya Indah Prathita Sutarno"},{"nim":"15113062","name":"Irene Idha Yovita"},{"nim":"15113063","name":"I Made Randhyan Brahmandita"},{"nim":"15113065","name":"Muhammad Mahlan Zuhdi Hanan"},{"nim":"15113066","name":"Ikhsan Rahmawan"},{"nim":"15113067","name":"Galmare Yulia Robert"},{"nim":"15113068","name":"Rany Aulianty"},{"nim":"15113069","name":"Abi Akbar W"},{"nim":"15113070","name":"Cahyo Nugroho"},{"nim":"15113071","name":"Windy Diwita Nisaekti"},{"nim":"15113072","name":"Dicky Afrizal"},{"nim":"15113073","name":"Muhammad Senna"},{"nim":"15113074","name":"Ryan Alfaedison"},{"nim":"15113075","name":"Heri Rasmanto"},{"nim":"15113076","name":"Vidya Aulia Puspasari"},{"nim":"15113077","name":"Mohammad Umair Dennyputra"},{"nim":"15113078","name":"Reynaldi Marchiano Indarno"},{"nim":"15113079","name":"Khaidir Sandyana Halim"},{"nim":"15113080","name":"Jatmiko Herjati"},{"nim":"15113081","name":"Helvina Oktavianti"},{"nim":"15113082","name":"Mumtaz Arafah"},{"nim":"15113083","name":"Billvian Frensi Dahal"},{"nim":"15113084","name":"Errandyno Rumengan"},{"nim":"15113085","name":"Nur Asriyah"},{"nim":"15113086","name":"Annas Rilo Pambudi Sussardi"},{"nim":"15113087","name":"Diviryan Abbiyu Alhaq"},{"nim":"15113088","name":"Suci Siti Aisah Robiansah"},{"nim":"15113089","name":"Jeshica Novalia"},{"nim":"15113090","name":"Prila Ayu Dwi Prastiwi"},{"nim":"15113091","name":"Leonardo Siburian"},{"nim":"15113092","name":"Lukman Guna Pribadi Supriyadi"},{"nim":"15113093","name":"Muhammad Naufal Ihsan"},{"nim":"15113094","name":"Jesika Taradini"},{"nim":"15113095","name":"Widianti Putri Ananda"},{"nim":"15113096","name":"Dwi Karina"},{"nim":"15113097","name":"Irma Prameshwari"},{"nim":"15113098","name":"Dewi Dharmayanti Hutabarat"},{"nim":"15113099","name":"Mochammad Agus Dewanto Perdana"},{"nim":"15113100","name":"Nafisatul Mardhiyah"}]